georss_client/__init__.py
georss_client/consts.py
georss_client/exceptions.py
georss_client/feed.py
georss_client/feed_entry.py
georss_client/feed_manager.py
georss_client/geo_rss_distance_helper.py
georss_client/xml_parser/__init__.py
georss_client/xml_parser/feed.py
georss_client/xml_parser/feed_dict_source.py
georss_client/xml_parser/feed_image.py
georss_client/xml_parser/feed_item.py
georss_client/xml_parser/feed_or_feed_item.py
georss_client/xml_parser/geometry.py
georss_client-0.18.dist-info/LICENSE
georss_client-0.18.dist-info/METADATA
georss_client-0.18.dist-info/WHEEL
georss_client-0.18.dist-info/top_level.txt
georss_client-0.18.dist-info/RECORD
