Metadata-Version: 2.1
Name: georss_client
Version: 0.18
Summary: A GeoRSS client library.
Author-email: Malte Franken <coding@subspace.de>
License: Apache License
Project-URL: Repository, https://github.com/exxamalte/python-georss-client
Project-URL: Issues, https://github.com/exxamalte/python-georss-client/issues
Project-URL: Changelog, https://github.com/exxamalte/python-georss-client/blob/main/CHANGELOG.md
Keywords: homeassistant,georss
Classifier: Programming Language :: Python :: 3.9
Classifier: Programming Language :: Python :: 3.10
Classifier: Programming Language :: Python :: 3.11
Classifier: Programming Language :: Python :: 3.12
Classifier: License :: OSI Approved :: Apache Software License
Classifier: Operating System :: OS Independent
Classifier: Development Status :: 5 - Production/Stable
Requires-Python: >=3.9
License-File: LICENSE
Requires-Dist: haversine>=2.8.1
Requires-Dist: xmltodict>=0.14.2
Requires-Dist: requests>=2.31.0
Requires-Dist: python-dateutil>=2.9.0
Provides-Extra: tests
Requires-Dist: pytest; extra == "tests"
Requires-Dist: pytest-timeout; extra == "tests"
Requires-Dist: pytest-xdist; extra == "tests"
Requires-Dist: pytest-cov; extra == "tests"
Requires-Dist: coverage; extra == "tests"
Requires-Dist: mock; extra == "tests"
